nvfsdp/__init__.py
nvfsdp/package_info.py
nvfsdp-0.0.0rc0.dist-info/licenses/LICENSE
nvfsdp-0.0.0rc0.dist-info/METADATA
nvfsdp-0.0.0rc0.dist-info/WHEEL
nvfsdp-0.0.0rc0.dist-info/top_level.txt
nvfsdp-0.0.0rc0.dist-info/RECORD
