Metadata-Version: 2.4
Name: nvFSDP
Version: 0.0.0rc0
Summary: nvFSDP - NVIDIA fork of Fully Sharded Data Parallelism that is cross-compatible with Megatron / TransformerEngine and native PyTorch.
Author-email: NVIDIA <nemo-toolkit@nvidia.com>
Maintainer-email: NVIDIA <nemo-toolkit@nvidia.com>
Project-URL: Download, https://github.com/NVIDIA-NeMo/nvFSDP/releases
Project-URL: Homepage, https://github.com/NVIDIA-NeMo/nvFSDP
Keywords: NLP,NeMo,deep,gpu,language,learning,machine,nvidia,pytorch,torch
Classifier: Development Status :: 5 - Production/Stable
Classifier: Environment :: Console
Classifier: Intended Audience :: Developers
Classifier: Intended Audience :: Information Technology
Classifier: Intended Audience :: Science/Research
Classifier: License :: OSI Approved :: Apache Software License
Classifier: Natural Language :: English
Classifier: Operating System :: OS Independent
Classifier: Programming Language :: Python :: 3
Classifier: Programming Language :: Python :: 3.10
Classifier: Topic :: Scientific/Engineering :: Artificial Intelligence
Classifier: Topic :: Scientific/Engineering :: Image Recognition
Classifier: Topic :: Scientific/Engineering :: Mathematics
Classifier: Topic :: Scientific/Engineering
Classifier: Topic :: Software Development :: Libraries :: Python Modules
Classifier: Topic :: Software Development :: Libraries
Classifier: Topic :: Utilities
Requires-Python: >=3.10
License-File: LICENSE
Requires-Dist: torch
Requires-Dist: packaging
Dynamic: license-file
